dash_breakpoints/WindowBreakpoints.py
dash_breakpoints/__init__.py
dash_breakpoints/_imports_.py
dash_breakpoints/dash_breakpoints.js
dash_breakpoints/metadata.json
dash_breakpoints/package-info.json
dash_breakpoints-0.1.0.dist-info/LICENSE
dash_breakpoints-0.1.0.dist-info/METADATA
dash_breakpoints-0.1.0.dist-info/WHEEL
dash_breakpoints-0.1.0.dist-info/top_level.txt
dash_breakpoints-0.1.0.dist-info/RECORD
