Metadata-Version: 1.1
Name: dash-breakpoints
Version: 0.1.0
Summary: Component to listen to the elements and window resize
Home-page: UNKNOWN
Author: Renaud Lainé <renaudlaine31@gmail.com>
Author-email: UNKNOWN
License: MIT
Platform: UNKNOWN
Classifier: Framework :: Dash
